analysis/__init__.py
analysis/from_df.py
example_jaeb-0.0.1.dist-info/LICENSE
example_jaeb-0.0.1.dist-info/METADATA
example_jaeb-0.0.1.dist-info/WHEEL
example_jaeb-0.0.1.dist-info/top_level.txt
example_jaeb-0.0.1.dist-info/RECORD
