Metadata-Version: 2.1
Name: example-jaeb
Version: 0.0.1
Summary: sample
Home-page: https://github.com/
Author: abba
Author-email: jaebin9274@cogniterm.com
License: MIT
Platform: UNKNOWN
Classifier: Programming Language :: Python :: 3
Classifier: License :: OSI Approved :: MIT License
Classifier: Operating System :: OS Independent
